pubplots/__init__.py
pubplots/pubplots.py
pubplots-0.1.1.dist-info/WHEEL
pubplots-0.1.1.dist-info/METADATA
pubplots-0.1.1.dist-info/RECORD
