Metadata-Version: 2.3
Name: pubplots
Version: 0.1.1
Summary: A small tool to help navigate the hellscape of preparing figures for scientific publishing.
Author: Graham Findlay
Author-email: Graham Findlay <gfindlay@wisc.com>
Requires-Dist: matplotlib>=3.6
Requires-Python: >=3.10
Project-URL: Repository, https://github.com/grahamfindlay/pubplots.git
